[
  {
    "title": "National 1st Prize — 22nd ROBOCON (ABU China Selection, MOE Class A)",
    "org": "Chinese Institute of Electronics",
    "date": "2023",
    "kind": "competition"
  },
  {
    "title": "National 2nd & 3rd Prize — 23rd ROBOCON (Operation & Programming Tracks)",
    "org": "Chinese Institute of Electronics",
    "date": "2024",
    "kind": "competition"
  },
  {
    "title": "National 2nd Prize — RoboCom Robot Developer Competition (Class A)",
    "org": "RoboCom",
    "date": "2024",
    "kind": "competition"
  },
  {
    "title": "Provincial 1st Prize — China Robot and AI Competition (Guangdong, Class A)",
    "org": "Chinese Association for Artificial Intelligence",
    "date": "2024",
    "kind": "competition"
  }
]
